[
  {
    "time": "2026-04-02 04:11:02.329433",
    "bot_id": "bot_v1",
    "activo": "BTC",
    "accion": "scan",
    "precio_fake": 65000
  },
  {
    "time": "2026-04-02 04:12:15.351388",
    "bot_id": "bot_v1",
    "activo": "BTC",
    "accion": "scan",
    "precio_fake": 65000
  },
  {
    "time": "2026-04-02 04:14:49.155932",
    "bot_id": "bot_v1",
    "activo": "BTC",
    "accion": "scan",
    "precio_fake": 65000
  },
  {
    "time": "2026-04-02 04:14:49.189617",
    "bot_id": "bot_v2",
    "activo": "BTC",
    "accion": "scan",
    "precio_fake": 65000
  },
  {
    "time": "2026-04-02 04:19:16.779466",
    "bot_id": "bot_v1",
    "activo": "BTC",
    "evento": "entry",
    "precio": 65355,
    "cantidad": 1
  },
  {
    "time": "2026-04-02 04:19:16.814643",
    "bot_id": "bot_v2",
    "activo": "BTC",
    "evento": "entry",
    "precio": 60591,
    "cantidad": 1
  },
  {
    "time": "2026-04-02 04:23:30.967236",
    "bot_id": "bot_v1",
    "activo": "BTC",
    "evento": "sl",
    "precio": 68329,
    "cantidad": 1
  },
  {
    "time": "2026-04-02 04:23:31.001917",
    "bot_id": "bot_v2",
    "activo": "BTC",
    "evento": "tp",
    "precio": 61313,
    "cantidad": 1
  },
  {
    "time": "2026-04-02 04:25:46.412786",
    "bot_id": "bot_v1",
    "activo": "BTC",
    "evento": "entry",
    "precio": 64846,
    "cantidad": 1
  },
  {
    "time": "2026-04-02 04:25:46.450917",
    "bot_id": "bot_v2",
    "activo": "BTC",
    "evento": "partial_tp",
    "precio": 61659,
    "cantidad": 1
  },
  {
    "time": "2026-04-02 04:28:16.972262",
    "bot_id": "bot_v1",
    "activo": "BTC",
    "evento": "partial_tp",
    "precio": 69069,
    "cantidad": 1
  },
  {
    "time": "2026-04-02 04:28:17.022094",
    "bot_id": "bot_v2",
    "activo": "BTC",
    "evento": "partial_tp",
    "precio": 63875,
    "cantidad": 1
  },
  {
    "time": "2026-04-02 04:29:21.923329",
    "bot_id": "bot_v1",
    "activo": "BTC",
    "evento": "tp",
    "precio": 66777,
    "cantidad": 1
  },
  {
    "time": "2026-04-02 04:29:21.958777",
    "bot_id": "bot_v2",
    "activo": "BTC",
    "evento": "tp",
    "precio": 63837,
    "cantidad": 1
  },
  {
    "time": "2026-04-02 05:00:09.670893",
    "bot_id": "bot_v1",
    "activo": "BTC",
    "evento": "tp",
    "precio": 68124,
    "cantidad": 1
  },
  {
    "time": "2026-04-02 05:00:09.713414",
    "bot_id": "bot_v2",
    "activo": "BTC",
    "evento": "sl",
    "precio": 63379,
    "cantidad": 1
  },
  {
    "time": "2026-04-02 05:08:03.829787",
    "bot_id": "bot_v1",
    "activo": "BTC",
    "evento": "tp",
    "precio": 67000,
    "cantidad": 1
  },
  {
    "time": "2026-04-02 05:08:03.865249",
    "bot_id": "bot_v2",
    "activo": "BTC",
    "evento": "entry",
    "precio": 63050,
    "cantidad": 1
  },
  {
    "time": "2026-04-02 05:09:15.074910",
    "bot_id": "bot_v1",
    "activo": "BTC",
    "evento": "partial_tp",
    "precio": 68790,
    "cantidad": 1
  },
  {
    "time": "2026-04-02 05:09:15.113199",
    "bot_id": "bot_v2",
    "activo": "BTC",
    "evento": "sl",
    "precio": 61774,
    "cantidad": 1
  },
  {
    "time": "2026-04-02 08:13:28.986788",
    "bot_id": "bot_v1",
    "activo": "BTC",
    "evento": "sl",
    "precio": 67398,
    "cantidad": 1
  },
  {
    "time": "2026-04-02 08:13:29.025254",
    "bot_id": "bot_v2",
    "activo": "BTC",
    "evento": "sl",
    "precio": 68633,
    "cantidad": 1
  },
  {
    "time": "2026-04-02 11:13:46.802345",
    "bot_id": "bot_v1",
    "activo": "BTC",
    "evento": "entry",
    "precio": 63684,
    "cantidad": 1
  },
  {
    "time": "2026-04-02 11:13:46.841880",
    "bot_id": "bot_v2",
    "activo": "BTC",
    "evento": "entry",
    "precio": 60797,
    "cantidad": 1
  },
  {
    "time": "2026-04-02 14:42:43.134339",
    "bot_id": "bot_v1",
    "activo": "BTC",
    "evento": "tp",
    "precio": 69284,
    "cantidad": 1
  },
  {
    "time": "2026-04-02 14:42:43.170723",
    "bot_id": "bot_v2",
    "activo": "BTC",
    "evento": "partial_tp",
    "precio": 63051,
    "cantidad": 1
  },
  {
    "time": "2026-04-02 17:38:24.754360",
    "bot_id": "bot_v1",
    "activo": "BTC",
    "evento": "sl",
    "precio": 66633,
    "cantidad": 1
  },
  {
    "time": "2026-04-02 17:38:24.793280",
    "bot_id": "bot_v2",
    "activo": "BTC",
    "evento": "tp",
    "precio": 62037,
    "cantidad": 1
  }
]